{
    "comment": "`절대 잠이 오지 않을 것 같다. 다른 걸 하는 건 어떨까?",
    "location": "#기숙사",
    "image": "https://i.ibb.co/C1r4nvC/30a670f0cc3b.jpg",
    "conditional": false,
    "getcon": [],
    "getgad": [],
    "lostcon": [],
    "lostgad": [],
    "revcon": [],
    "revgad": [],
    "choices": [
        {
            "text": "휴대폰을 본다.",
            "link": "111008 111002 0",
            "conreq": false,
            "gadreq": false,
            "condition": [],
            "gadget": []
        },
        {
            "text": "일어난다.",
            "link": "111008 111003 1",
            "conreq": false,
            "gadreq": false,
            "condition": [],
            "gadget": []
        },
        {
            "text": "잔다.",
            "link": "111008 111042 2",
            "conreq": false,
            "gadreq": false,
            "condition": [],
            "gadget": []
        },
        {
            "text": "-",
            "link": "111008 0 3",
            "conreq": false,
            "gadreq": false,
            "condition": [],
            "gadget": []
        },
        {
            "text": "-",
            "link": "111008 0 4",
            "conreq": false,
            "gadreq": false,
            "condition": [],
            "gadget": []
        },
        {
            "text": "-",
            "link": "111008 0 5",
            "conreq": false,
            "gadreq": false,
            "condition": [],
            "gadget": []
        }
    ]
}