{
    "comment": "`기숙사 문이 드디어 열렸다. 밖으로 나가서 집으로 돌아갈 방법을 생각해보자.",
    "location": "#기숙사",
    "image": "https://i.ibb.co/TcrMxGr/9c1c63a07f74.jpg",
    "conditional": false,
    "getcon": [],
    "getgad": [],
    "lostcon": [],
    "lostgad": [],
    "revcon": [],
    "revgad": [],
    "choices": [
        {
            "text": "나간다",
            "link": "111028 112001 0",
            "conreq": false,
            "gadreq": false,
            "condition": [],
            "gadget": []
        },
        {
            "text": "-",
            "link": "111028 0 1",
            "conreq": false,
            "gadreq": false,
            "condition": [],
            "gadget": []
        },
        {
            "text": "-",
            "link": "111028 0 2",
            "conreq": false,
            "gadreq": false,
            "condition": [],
            "gadget": []
        },
        {
            "text": "-",
            "link": "111028 0 3",
            "conreq": false,
            "gadreq": false,
            "condition": [],
            "gadget": []
        },
        {
            "text": "-",
            "link": "111028 0 4",
            "conreq": false,
            "gadreq": false,
            "condition": [],
            "gadget": []
        },
        {
            "text": "-",
            "link": "111028 0 5",
            "conreq": false,
            "gadreq": false,
            "condition": [],
            "gadget": []
        }
    ]
}